{
  "견적번호": "",
  "견적일자": "APR 1. 2025",
  "거래처명": "주니퍼 네트웍스",
  "카테고리": [
    {
      "category": "기획/Concept",
      "amount": 1350000,
      "items": [
        {
          "품목명": "아트워크 /Artwork Visual 아트워크 표지 및 회사소개",
          "수량": "",
          "단가": 200000,
          "금액": 200000
        },
        {
          "품목명": "시안비 /Layout Design 시안 및 수정 (앞, 후면)",
          "수량": "",
          "단가": 500000,
          "금액": 500000
        },
        {
          "품목명": "편집비 /Typesetting 편집 및 화판 (앞, 후면)",
          "수량": "",
          "단가": 650000,
          "금액": 650000
        },
        {
          "품목명": "기타/Others",
          "수량": "",
          "단가": "",
          "금액": 0
        }
      ]
    },
    {
      "category": "분해/Separation",
      "amount": 0,
      "items": []
    },
    {
      "category": "소부/Plate Burning & Printing",
      "amount": 232000,
      "items": [
        {
          "품목명": "소부/Plate Burning & 주니퍼 2절 양면 × 4도",
          "수량": 8,
          "단가": 15000,
          "금액": 120000
        },
        {
          "품목명": "인쇄비 /Printing 주니퍼 국전 양면 8도 × 1R",
          "수량": 8,
          "단가": 14000,
          "금액": 112000
        }
      ]
    },
    {
      "category": "인쇄용지 /Paper",
      "amount": 725000,
      "items": [
        {
          "품목명": "랑데뷰 105 GSM",
          "수량": 2.9,
          "단가": 250000,
          "금액": 725000
        }
      ]
    },
    {
      "category": "코팅/Coating",
      "amount": 0,
      "items": []
    },
    {
      "category": "접지/Folding",
      "amount": 500000,
      "items": [
        {
          "품목명": "특수 접지",
          "수량": 1000,
          "단가": 500000,
          "금액": 500000
        }
      ]
    },
    {
      "category": "기타/Others",
      "amount": 193000,
      "items": [
        {
          "품목명": "택배발송 (포장박스 포함)",
          "수량": "",
          "단가": "",
          "금액": 0
        },
        {
          "품목명": "기타 비용",
          "수량": "",
          "단가": "",
          "금액": 193000
        }
      ]
    }
  ],
  "합계금액": 3000000,
  "세액": 300000,
  "총액": 3300000
}