{
  "meta": {
    "file_name": "견적서_(주)유스튜디오_20250219_(aws summit )_에프원마케팅_배성기실장_ver2.xlsx"
  },
  "items": [
    {
      "description": "트랙 촬영",
      "unit_krw": 1800000,
      "quantity": 10,
      "unit": null,
      "amount": 36000000,
      "remark": ""
    },
    {
      "description": "카메라",
      "unit_krw": null,
      "quantity": 1,
      "unit": null,
      "amount": null,
      "remark": ""
    },
    {
      "description": "콘솔 장비",
      "unit_krw": null,
      "quantity": 1,
      "unit": null,
      "amount": null,
      "remark": ""
    },
    {
      "description": "촬영 감독",
      "unit_krw": null,
      "quantity": 1,
      "unit": null,
      "amount": null,
      "remark": ""
    },
    {
      "description": "콘솔 인력",
      "unit_krw": null,
      "quantity": 1,
      "unit": null,
      "amount": null,
      "remark": ""
    },
    {
      "description": "편집",
      "unit_krw": null,
      "quantity": null,
      "unit": null,
      "amount": null,
      "remark": ""
    },
    {
      "description": "트랙 편집",
      "unit_krw": 600000,
      "quantity": 10,
      "unit": null,
      "amount": 12000000,
      "remark": "템플릿 화 편집 부분 수정 트랙별"
    },
    {
      "description": "추가 사항",
      "unit_krw": null,
      "quantity": null,
      "unit": null,
      "amount": null,
      "remark": ""
    },
    {
      "description": "트랙 2,3,4 대포 렌즈 추가",
      "unit_krw": 800000,
      "quantity": 3,
      "unit": null,
      "amount": null,
      "remark": ""
    },
    {
      "description": "라이브 송출",
      "unit_krw": 1000000,
      "quantity": 10,
      "unit": null,
      "amount": null,
      "remark": ""
    },
    {
      "description": "촬영 감독",
      "unit_krw": null,
      "quantity": 1,
      "unit": null,
      "amount": null,
      "remark": ""
    },
    {
      "description": "콘솔 인력",
      "unit_krw": null,
      "quantity": 1,
      "unit": null,
      "amount": null,
      "remark": ""
    },
    {
      "description": "월,화 리허설 및 셋팅 비용",
      "unit_krw": 1500000,
      "quantity": 10,
      "unit": null,
      "amount": 15000000,
      "remark": ""
    }
  ],
  "header": {},
  "summary": {}
}